README.md
setup.cfg
setup.py
fixture_utils/__init__.py
fixture_utils/exceptions.py
fixture_utils/fixture.py
fixture_utils/fixture_manager.py
fixture_utils.egg-info/PKG-INFO
fixture_utils.egg-info/SOURCES.txt
fixture_utils.egg-info/dependency_links.txt
fixture_utils.egg-info/not-zip-safe
fixture_utils.egg-info/top_level.txt